LICENSE
README.md
pyproject.toml
setup.py
chia_base/__init__.py
chia_base/py.typed
chia_base.egg-info/PKG-INFO
chia_base.egg-info/SOURCES.txt
chia_base.egg-info/dependency_links.txt
chia_base.egg-info/requires.txt
chia_base.egg-info/top_level.txt
chia_base/atoms/__init__.py
chia_base/atoms/hexbytes.py
chia_base/atoms/ints.py
chia_base/atoms/sized_bytes.py
chia_base/atoms/struct_stream.py
chia_base/bls12_381/__init__.py
chia_base/bls12_381/bls_public_key.py
chia_base/bls12_381/bls_secret_exponent.py
chia_base/bls12_381/bls_signature.py
chia_base/bls12_381/secret_key_utils.py
chia_base/cbincode/__init__.py
chia_base/cbincode/parser.py
chia_base/cbincode/streamer.py
chia_base/cbincode/util.py
chia_base/contrib/__init__.py
chia_base/contrib/bech32m.py
chia_base/core/__init__.py
chia_base/core/coin.py
chia_base/core/coin_spend.py
chia_base/core/conlang.py
chia_base/core/spend_bundle.py
chia_base/meta/__init__.py
chia_base/meta/optional.py
chia_base/meta/type_tree.py
chia_base/meta/typing.py
chia_base/util/__init__.py
chia_base/util/bech32.py
chia_base/util/std_hash.py
tests/test_bls.py
tests/test_core.py
tests/test_streamable.py